mditor/__init__.py
mditor/configs.py
mditor/fields.py
mditor/urls.py
mditor/views.py
mditor/widgets.py
mditor/static/mditor/css/highlight.css
mditor/static/mditor/css/highlight.min.css
mditor/static/mditor/css/mditor.css
mditor/static/mditor/css/mditor.min.css
mditor/static/mditor/font/674f50d287a8c48dc19ba404d20fe713.eot
mditor/static/mditor/font/912ec66d7572ff821749319396470bde.svg
mditor/static/mditor/font/a48ac41620cd818c5020d0f4302489ff.ttf
mditor/static/mditor/font/af7ae505a9eed503f8b8e6982036873e.woff2
mditor/static/mditor/font/b06871f281fee6b241d60582ae9369b9.ttf
mditor/static/mditor/font/fee66e712a8a08eef5805a46892932ad.woff
mditor/static/mditor/js/mditor.js
mditor/static/mditor/js/mditor.min.js
mditor/templates/mditor/widget.html
django_mditor-0.0.11.dist-info/LICENSE
django_mditor-0.0.11.dist-info/METADATA
django_mditor-0.0.11.dist-info/WHEEL
django_mditor-0.0.11.dist-info/top_level.txt
django_mditor-0.0.11.dist-info/RECORD
