Metadata-Version: 2.1
Name: django-mditor
Version: 0.0.11
Summary: A simple Django app to edit markdown text.
Author-email: 敬晓兵 <ju4t@qq.com>
License: MIT License
Project-URL: Homepage, https://labdoc.cc/article/10/
Project-URL: Bug Tracker, https://github.com/ju4t/mditor/issues
Classifier: Programming Language :: Python :: 3
Classifier: License :: OSI Approved :: MIT License
Classifier: Operating System :: OS Independent
Requires-Python: >=3.6
License-File: LICENSE
